spatial_memory/__init__.py
spatial_memory/__main__.py
spatial_memory/config.py
spatial_memory/py.typed
spatial_memory/server.py
spatial_memory/verify.py
spatial_memory/adapters/__init__.py
spatial_memory/adapters/lancedb_repository.py
spatial_memory/core/__init__.py
spatial_memory/core/connection_pool.py
spatial_memory/core/database.py
spatial_memory/core/embeddings.py
spatial_memory/core/errors.py
spatial_memory/core/file_security.py
spatial_memory/core/health.py
spatial_memory/core/helpers.py
spatial_memory/core/import_security.py
spatial_memory/core/lifecycle_ops.py
spatial_memory/core/logging.py
spatial_memory/core/metrics.py
spatial_memory/core/models.py
spatial_memory/core/rate_limiter.py
spatial_memory/core/security.py
spatial_memory/core/spatial_ops.py
spatial_memory/core/utils.py
spatial_memory/core/validation.py
spatial_memory/ports/__init__.py
spatial_memory/ports/repositories.py
spatial_memory/services/__init__.py
spatial_memory/services/export_import.py
spatial_memory/services/lifecycle.py
spatial_memory/services/memory.py
spatial_memory/services/spatial.py
spatial_memory/services/utility.py
spatial_memory_mcp-1.0.0.dist-info/METADATA
spatial_memory_mcp-1.0.0.dist-info/WHEEL
spatial_memory_mcp-1.0.0.dist-info/entry_points.txt
spatial_memory_mcp-1.0.0.dist-info/licenses/LICENSE
spatial_memory_mcp-1.0.0.dist-info/RECORD
