Metadata-Version: 2.4
Name: spatial-memory-mcp
Version: 1.0.0
Summary: Spatial bidirectional persistent memory MCP server for LLMs - vector-based semantic memory as a navigable landscape
Project-URL: Homepage, https://github.com/arman-tech/spatial-memory-mcp
Project-URL: Repository, https://github.com/arman-tech/spatial-memory-mcp
Author: Jon
License: MIT
License-File: LICENSE
Keywords: embeddings,llm,mcp,memory,semantic-search,spatial,vector
Classifier: Development Status :: 5 - Production/Stable
Classifier: Intended Audience :: Developers
Classifier: License :: OSI Approved :: MIT License
Classifier: Programming Language :: Python :: 3
Classifier: Programming Language :: Python :: 3.10
Classifier: Programming Language :: Python :: 3.11
Classifier: Programming Language :: Python :: 3.12
Classifier: Programming Language :: Python :: 3.13
Requires-Python: >=3.10
Requires-Dist: hdbscan>=0.8.33
Requires-Dist: lancedb>=0.27.0
Requires-Dist: mcp>=1.0.0
Requires-Dist: numpy>=1.24.0
Requires-Dist: pydantic-settings>=2.0.0
Requires-Dist: pydantic>=2.0.0
Requires-Dist: sentence-transformers[onnx]>=2.2.0
Requires-Dist: umap-learn>=0.5.5
Provides-Extra: dev
Requires-Dist: mypy>=1.0.0; extra == 'dev'
Requires-Dist: prometheus-client>=0.20.0; extra == 'dev'
Requires-Dist: pytest-asyncio>=0.21.0; extra == 'dev'
Requires-Dist: pytest-cov>=4.0.0; extra == 'dev'
Requires-Dist: pytest>=7.0.0; extra == 'dev'
Requires-Dist: ruff>=0.1.0; extra == 'dev'
Provides-Extra: metrics
Requires-Dist: prometheus-client>=0.20.0; extra == 'metrics'
Provides-Extra: openai
Requires-Dist: openai>=1.0.0; extra == 'openai'
Requires-Dist: tiktoken>=0.5.0; extra == 'openai'
